aziona/__init__.py
aziona/__main__.py
aziona/cli/__init__.py
aziona/cli/main.py
aziona/cli/parser/__init__.py
aziona/cli/parser/parser.py
aziona/cli/parser/v1/__init__.py
aziona/cli/parser/v1/driver.py
aziona/cli/parser/v1/schema.json
aziona/core/__init__.py
aziona/core/argparser.py
aziona/core/commands.py
aziona/core/files.py
aziona/core/gitmanager.py
aziona/core/http.py
aziona/core/io.py
aziona/core/log.py
aziona/core/text.py
aziona/core/conf/__init__.py
aziona/core/conf/const.py
aziona/core/conf/errors.py
aziona/core/conf/session.py
aziona/core/conf/settings.py
aziona/packages/__init__.py
aziona/packages/aziona.py
aziona/packages/aws/__init__.py
aziona/packages/aws/awscli.py
aziona/packages/aws/resource_api.py
aziona/packages/aws/resource_session.py
aziona/packages/aws/iam/__init__.py
aziona/packages/aws/iam/assume_role.py
aziona/packages/aws/iam/create_policy.py
aziona/packages/aws/iam/create_role.py
aziona/packages/aws/iam/delete_policy.py
aziona/packages/aws/iam/delete_role.py
aziona/packages/aws/iam/identity.py
aziona/packages/aws/route53/__init__.py
aziona/packages/aws/route53/dns_record.py
aziona/packages/aws/route53/dns_record_alias.py
aziona/packages/aws/route53/hosted_zone.py
aziona/packages/cloudflare/__init__.py
aziona/packages/cloudflare/dns_create.py
aziona/packages/cloudflare/dns_delete.py
aziona/packages/cloudflare/dns_update.py
aziona/packages/docker/__init__.py
aziona/packages/docker/build.py
aziona/packages/docker/login.py
aziona/packages/docker/login_aws_credentials.py
aziona/packages/docker/push.py
aziona/packages/docker/tag.py
aziona/packages/kubernetes/__init__.py
aziona/packages/kubernetes/eksctl.py
aziona/packages/kubernetes/functions.py
aziona/packages/kubernetes/helm.py
aziona/packages/kubernetes/iam_service_account.py
aziona/packages/kubernetes/kubeaction.py
aziona/packages/kubernetes/kubeconfig.py
aziona/packages/terraform/__init__.py
aziona/packages/terraform/terraform.py
aziona/packages/utils/__init__.py
aziona-0.1.16.dist-info/LICENSE
aziona-0.1.16.dist-info/METADATA
aziona-0.1.16.dist-info/WHEEL
aziona-0.1.16.dist-info/top_level.txt
aziona-0.1.16.dist-info/RECORD
