Metadata-Version: 2.1
Name: aziona
Version: 0.1.16
Summary: aziona cli
Home-page: https://github.com/azionaventures/aziona
Author: Azionaventures
Author-email: tech@azionaventures.com
License: GPL-3.0 License
Platform: UNKNOWN
Classifier: Programming Language :: Python :: 3
Classifier: Programming Language :: Python :: 3.6
Classifier: Programming Language :: Python :: 3.7
Classifier: Programming Language :: Python :: 3.8
Classifier: Operating System :: OS Independent
Requires-Python: >= 3.6
Requires-Dist: GitPython (==3.1.*)
Requires-Dist: PyYAML (==5.*)
Requires-Dist: awscli (==1.*)
Requires-Dist: boto3 (==1.*)
Requires-Dist: distro (==1.*)
Requires-Dist: jsonschema (>=3.2.0)
Requires-Dist: pathlib2 (==2.*)
Requires-Dist: requests
